{
    "home_team_stats": [],
    "away_team_stats": [],
    "match_stats": [],
    "ballpo": [],
    "shots": [],
    "totpas": [],
    "faltas": [
        {
            "text": "se convirtió en el partido con menos faltas de la temporada, con {stat_val} faltas",
            "condition": "!has_stat_team && !is_stat_positive"
        },
        {
            "text": "se convirtió en el partido con más faltas de la temporada, con {stat_val} faltas",
            "condition": "!has_stat_team && is_stat_positive"
        },
        {
            "text": "sufrió {stat_val} faltas, la mayor cantidad de toda la competición",
            "condition": "has_stat_team && is_stat_positive && is_stat_global"
        },
        {
            "text": "sufrió {stat_val} faltas, la mayor cantidad hasta ahora",
            "condition": "has_stat_team && is_stat_positive && !is_stat_global"
        },
        {
            "text": "sufrió solo {stat_val} faltas, la menor cantidad de toda la competición",
            "condition": "has_stat_team && !is_stat_positive && is_stat_global"
        },
        {
            "text": "solo sufrió {stat_val} faltas, su mínimo hasta el momento",
            "condition": "has_stat_team && !is_stat_positive && !is_stat_global"
        }
    ],
    "foul": [
        {
            "text": "cometió la mayor cantidad de faltas de la temporada con un total de {stat_val}",
            "condition": "has_stat_team && is_stat_positive && is_stat_global"
        },
        {
            "text": "cometió la menor cantidad de faltas de la temporada con solo {stat_val}",
            "condition": "has_stat_team && !is_stat_positive && is_stat_global"
        },
        {
            "text": "cometió su mayor número de faltas de la temporada con un total de {stat_val}",
            "condition": "has_stat_team && is_stat_positive && !is_stat_global"
        },
        {
            "text": "cometió su menor cantidad de faltas de la temporada con solo {stat_val}",
            "condition": "has_stat_team && !is_stat_positive && !is_stat_global"
        },
        {
            "text": "se cometieron {stat_val} faltas, convirtiéndose en el partido con más faltas de la temporada",
            "condition": "!has_stat_team && is_stat_positive"
        },
        {
            "text": "se cometieron apenas {stat_val} faltas, el número más bajo en la competición",
            "condition": "!has_stat_team && !is_stat_positive"
        }
    ],
    "corner": [
        {
            "text": "hubo apenas {#arg.value} córneres, el número más bajo esta temporada",
            "condition": "!has_stat_team && is_stat_positive"
        },
        {
            "text": "se batió el récord de saques de esquina, con un total de {stat_val}",
            "condition": "!has_stat_team && is_stat_positive"
        },
        {
            "text": "batió el récord de córneres en la competición, con un total de {stat_val}",
            "condition": "has_stat_team && is_stat_positive && is_stat_global"
        },
        {
            "text": "batió su récord de córneres en la competición, con un total de {stat_val}",
            "condition": "has_stat_team && is_stat_positive && !is_stat_global"
        },
        {
            "text": "lanzó apenas {stat_val} córneres, el número más bajo de toda la competición",
            "condition": "has_stat_team && !is_stat_positive && is_stat_global"
        },
        {
            "text": "lanzó apenas {stat_val} córneres, su número más bajo en la competición",
            "condition": "has_stat_team && !is_stat_positive && !is_stat_global"
        },
        {
            "text": "hubo apenas {stat_val} córneres, el número más bajo esta temporada",
            "condition": "!has_stat_team && !is_stat_positive"
        }
    ],
    "offs": [
        {
            "text": "menor número de fueras de juego registrados - {stat_val}",
            "condition": "!has_stat_team && !is_stat_positive"
        },
        {
            "text": "mayor número de fueras de juego registrados - {stat_val}",
            "condition": "!has_stat_team && is_stat_positive"
        },
        {
            "text": "estuvo en fuera de juego {stat_val} veces, la cifra más alta hasta ahora en toda la competición",
            "condition": "has_stat_team && is_stat_positive && is_stat_global"
        },
        {
            "text": "estuvo en fuera de juego {stat_val} veces, su cifra más alta hasta ahora en toda la competición",
            "condition": "has_stat_team && is_stat_positive && !is_stat_global"
        },
        {
            "text": "estuvo en fuera de juego {stat_val} veces, la cifra baja hasta ahora en toda la competición",
            "condition": "has_stat_team && !is_stat_positive && is_stat_global"
        },
        {
            "text": "estuvo en fuera de juego {stat_val} veces, su mejor registro en la competición",
            "condition": "has_stat_team && !is_stat_positive && !is_stat_global"
        }
    ],
    "shot": [],
    "winningless_streak": [],
    "losing_streak": [],
    "winning_streak": [],
    "drawing_streak": [],
    "lossless_streak": [
        {
            "text": "Extendió una racha de {post_curiosity_val} partidos sin perder",
            "condition": "post_curiosity_val > 3"
        },
        {
            "text": "Alargó una racha de {post_curiosity_val} partidos sin perder",
            "condition": "post_curiosity_val > 3"
        }
    ],
    "no_goals_conceded_streak": [],
    "goals_scored_streak": [],
    "shotgo": [],
    "gksave": [
        {
            "text": "batió su récord de paradas en la temporada, con {#arg.value} paradas",
            "condition": "has_stat_team && is_stat_positive && !is_stat_global"
        },
        {
            "text": "hizo apenas {#arg.value} paradas, su número más bajo esta temporada",
            "condition": "has_stat_team && !is_stat_positive && !is_stat_global"
        },
        {
            "text": "batió el récord de paradas en la temporada, con {#arg.value} paradas",
            "condition": "has_stat_team && is_stat_positive && is_stat_global"
        },
        {
            "text": "hizo apenas {#arg.value} paradas, el número más bajo esta temporada",
            "condition": "has_stat_team && !is_stat_positive && is_stat_global"
        }
    ],
    "games_without_winning": [
        {
            "text": "Perdió puntos por primera vez",
            "condition": "pre_curiosity_val == 0 && post_curiosity_val > 0"
        }
    ],
    "losses": [
        {
            "text": "Perdió su primer partido en la competición",
            "condition": "pre_curiosity_val == 0 && post_curiosity_val > 0"
        }
    ]
}